damagedetection/damagedetection.py
damagedetection-0.0.1.dist-info/LICENSE
damagedetection-0.0.1.dist-info/METADATA
damagedetection-0.0.1.dist-info/WHEEL
damagedetection-0.0.1.dist-info/entry_points.txt
damagedetection-0.0.1.dist-info/top_level.txt
damagedetection-0.0.1.dist-info/RECORD
