Metadata-Version: 2.1
Name: damagedetection
Version: 0.0.1
Summary: Disaster Damage Detector
Author-email: Pranya Chandratre <pranya.chandratre@gmail.com>
Classifier: Programming Language :: Python :: 3
Classifier: License :: OSI Approved :: MIT License
Classifier: Operating System :: OS Independent
Requires-Python: >=3.7
License-File: LICENSE
Requires-Dist: pillow
Requires-Dist: folium
Requires-Dist: numpy
Requires-Dist: pandas
Requires-Dist: tensorflow
